finufft/libfinufft.dll
finufft/_finufft.py
finufft/_interfaces.py
finufft/__init__.py
finufft-2.4.1.dist-info/DELVEWHEEL
finufft-2.4.1.dist-info/METADATA
finufft-2.4.1.dist-info/RECORD
finufft-2.4.1.dist-info/WHEEL
finufft.libs/.load-order-finufft-2.4.1
finufft.libs/libfftw3-3-8da03c819386f322fa060b460872a182.dll
finufft.libs/libfftw3f-3-68e4ebbe3923cb7a9405827c92378dec.dll
finufft.libs/libfftw3f_omp-3-e0a93fa6acb0bb214734ac7b69b9f95b.dll
finufft.libs/libfftw3_omp-3-31e685fea8d246729c98d5b29f4f03f1.dll
finufft.libs/libgcc_s_seh-1-40ceb3e05a395bf3093887862e02130b.dll
finufft.libs/libgomp-1-b35eadb91bce6b033844cecf2131d83d.dll
finufft.libs/libstdc++-6-b0ad8744b53d33b320fd50fbb97fc287.dll
finufft.libs/libwinpthread-1-5b611d7f064f54e473bf27783ab448dc.dll
