Metadata-Version: 2.1
Name: finufft
Version: 2.4.1
Summary: Python interface to FINUFFT
Author: Jeremy Magland, Daniel Foreman-Mackey, Joakim Anden, Libin Lu, Marco Barbone, Robert Blackwell, Alex Barnett
Maintainer-Email: Alex Barnett <abarnett@flatironinstitute.org>
Classifier: License :: OSI Approved :: Apache Software License
Classifier: Programming Language :: Python :: 3
Classifier: Programming Language :: C++
Classifier: Operating System :: POSIX :: Linux
Classifier: Operating System :: MacOS :: MacOS X
Classifier: Operating System :: Microsoft :: Windows
Requires-Python: >=3.8
Requires-Dist: numpy>=1.12.0
Requires-Dist: packaging
